mailjet_rest/__init__.py
mailjet_rest/_version.py
mailjet_rest/client.py
mailjet_rest/utils/__init__.py
mailjet_rest/utils/version.py
mailjet_rest-1.5.0.dist-info/licenses/LICENSE
samples/__init__.py
samples/campaign_sample.py
samples/contacts_sample.py
samples/email_template_sample.py
samples/getting_started_sample.py
samples/new_sample.py
samples/parse_api_sample.py
samples/segments_sample.py
samples/sender_and_domain_samples.py
samples/statistic_sample.py
tests/__init__.py
tests/test_client.py
tests/test_version.py
tests/doc_tests/files/data.csv
mailjet_rest-1.5.0.dist-info/METADATA
mailjet_rest-1.5.0.dist-info/WHEEL
mailjet_rest-1.5.0.dist-info/top_level.txt
mailjet_rest-1.5.0.dist-info/RECORD
